micropip/__init__.py
micropip/_mock_package.py
micropip/_utils.py
micropip/_version.py
micropip/constants.py
micropip/freeze.py
micropip/install.py
micropip/list.py
micropip/logging.py
micropip/metadata.py
micropip/package.py
micropip/package_index.py
micropip/package_manager.py
micropip/py.typed
micropip/transaction.py
micropip/uninstall.py
micropip/wheelinfo.py
micropip/_compat/__init__.py
micropip/_compat/_compat_in_pyodide.py
micropip/_compat/_compat_not_in_pyodide.py
micropip/_compat/compatibility_layer.py
micropip/externals/__init__.py
micropip/externals/mousebender/simple.py
micropip-0.7.0.dist-info/LICENSE
micropip-0.7.0.dist-info/METADATA
micropip-0.7.0.dist-info/WHEEL
micropip-0.7.0.dist-info/top_level.txt
micropip-0.7.0.dist-info/RECORD
