Metadata-Version: 2.1
Name: micropip
Version: 0.7.0
Summary: A lightweight Python package installer for the web
Author: Pyodide developers
License: Mozilla Public License Version 2.0
Project-URL: Homepage, https://github.com/pyodide/micropip
Project-URL: Bug Tracker, https://github.com/pyodide/micropip/issues
Classifier: Programming Language :: Python :: 3
Classifier: License :: OSI Approved :: Mozilla Public License 2.0 (MPL 2.0)
Classifier: Operating System :: OS Independent
Requires-Python: >=3.10
License-File: LICENSE
Requires-Dist: packaging>=23.0
Provides-Extra: test
Requires-Dist: pytest-httpserver; extra == "test"
Requires-Dist: pytest-pyodide; extra == "test"
Requires-Dist: pytest-cov; extra == "test"
Requires-Dist: pytest<8.0.0; extra == "test"
Requires-Dist: build==0.7.0; extra == "test"
